django_maintain-1.0.0.dist-info/METADATA
django_maintain-1.0.0.dist-info/RECORD
django_maintain-1.0.0.dist-info/WHEEL
django_maintain-1.0.0.dist-info/top_level.txt
maintain/__init__.py
maintain/middleware.py
